{
  "playtime_seconds": 486.4498782157898,
  "enemies_defeated": 33,
  "quests_cleared": 0,
  "gold_collected": 265,
  "chests_opened": 0,
  "player_hp": 30,
  "player_max_hp": 30,
  "dungeon_cleared": false,
  "current_location": "dungeon",
  "player_floor": 4,
  "inventory_data": [
    {
      "type": "PotionItem",
      "kwargs": {},
      "stack_count": 33
    },
    {
      "type": "DebugSwordItem",
      "kwargs": {
        "upgrade_level": 0
      },
      "stack_count": 1
    },
    {
      "type": "GoldItem",
      "kwargs": {
        "amount": 265
      },
      "stack_count": 265
    },
    {
      "type": "CandleItem",
      "kwargs": {},
      "stack_count": 20
    },
    {
      "type": "RoomKeyItem",
      "kwargs": {},
      "stack_count": 1
    },
    {
      "type": "FloorKeyItem",
      "kwargs": {},
      "stack_count": 1
    },
    {
      "type": "FloorKeyItem",
      "kwargs": {},
      "stack_count": 1
    },
    {
      "type": "RoomKeyItem",
      "kwargs": {},
      "stack_count": 1
    }
  ],
  "door_states": [
    false,
    false,
    true,
    false
  ],
  "chest_states": [
    {
      "opened": false,
      "items": [
        {
          "type": "PotionItem",
          "kwargs": {},
          "stack_count": 1
        },
        {
          "type": "GoldItem",
          "kwargs": {
            "amount": 10
          },
          "stack_count": 1
        },
        {
          "type": "PotionItem",
          "kwargs": {},
          "stack_count": 1
        }
      ]
    },
    {
      "opened": false,
      "items": [
        {
          "type": "PotionItem",
          "kwargs": {},
          "stack_count": 1
        },
        {
          "type": "GoldItem",
          "kwargs": {
            "amount": 10
          },
          "stack_count": 1
        }
      ]
    },
    {
      "opened": false,
      "items": [
        {
          "type": "GoldItem",
          "kwargs": {
            "amount": 10
          },
          "stack_count": 1
        },
        {
          "type": "GoldItem",
          "kwargs": {
            "amount": 15
          },
          "stack_count": 1
        },
        {
          "type": "GoldItem",
          "kwargs": {
            "amount": 10
          },
          "stack_count": 1
        },
        {
          "type": "PotionItem",
          "kwargs": {},
          "stack_count": 1
        },
        {
          "type": "PotionItem",
          "kwargs": {},
          "stack_count": 1
        }
      ]
    }
  ],
  "armour_data": {
    "helmet": null,
    "chestplate": null,
    "leggings": null,
    "boots": null
  },
  "stats_data": {
    "level": 1,
    "exp": 75,
    "stat_points": 0,
    "dexterity": 0,
    "strength": 0,
    "magic_mastery": 0
  },
  "quest_data": {
    "active": [],
    "completed": [],
    "available": [
      "clear_dungeon",
      "kill_trolls_3",
      "survive_10_rounds",
      "kill_lich_king"
    ]
  },
  "floor_states_data": {
    "1": {
      "unlocked_doors": [
        "key_to_chest",
        "floor_circle",
        "key_to_chieftain",
        "key_to_circle"
      ]
    },
    "2": {
      "unlocked_doors": [
        "key_a_to_b",
        "key_c_to_big",
        "key_spawn_to_a",
        "key_b_to_c",
        "floor_circle",
        "key_d_to_e",
        "key_b_to_d"
      ]
    },
    "3": {
      "unlocked_doors": [
        "key_floor_circle",
        "floor_circle",
        "key_big_to_small",
        "key_hub_to_big"
      ]
    },
    "4": {
      "unlocked_doors": [
        "key_r2_to_arena",
        "key_r1_to_r2",
        "key_spawn_to_r1"
      ]
    }
  },
  "save_time": "2026-03-20  11:09",
  "slot": 0
}